API/__init__.py
API/paymentAPI.py
base/__init__.py
base/payubase.py
constants/__init__.py
constants/payuconstants.py
errors/__init__.py
errors/payuerrors.py
payu/__init__.py
payu/payuClient.py
payu/API/__init__.py
payu/API/paymentAPI.py
payu/base/__init__.py
payu/base/payubase.py
payu/constants/__init__.py
payu/constants/payuconstants.py
payu/errors/__init__.py
payu/errors/payuerrors.py
payu/request/PayURequest.py
payu/request/__init__.py
payu/resources/__init__.py
payu/resources/hasher.py
payu_websdk/__init__.py
payu_websdk/payuClient.py
request/PayURequest.py
request/__init__.py
resources/__init__.py
resources/hasher.py
payu_websdk-0.1.7.dist-info/LICENSE
payu_websdk-0.1.7.dist-info/METADATA
payu_websdk-0.1.7.dist-info/WHEEL
payu_websdk-0.1.7.dist-info/top_level.txt
payu_websdk-0.1.7.dist-info/RECORD
