Metadata-Version: 2.1
Name: payu-websdk
Version: 0.1.7
Summary: PayU
Home-page: https://github.com/payu-india/web-sdk-python
Author: PayU Web SDK for Python
Author-email: integration@payu.in
License: MIT
Classifier: Programming Language :: Python :: 3
Classifier: Operating System :: OS Independent
Classifier: License :: OSI Approved :: MIT License
License-File: LICENSE
Requires-Dist: requests
